wsapi_client/__init__.py
wsapi_client/client.py
wsapi_client/exceptions.py
wsapi_client/http.py
wsapi_client/api/account.py
wsapi_client/api/calls.py
wsapi_client/api/chats.py
wsapi_client/api/contacts.py
wsapi_client/api/groups.py
wsapi_client/api/instance.py
wsapi_client/api/media.py
wsapi_client/api/messages.py
wsapi_client/api/session.py
wsapi_client/api/users.py
wsapi_client/events/factory.py
wsapi_client/models/problem_details.py
wsapi_client/models/constants/__init__.py
wsapi_client/models/constants/event_types.py
wsapi_client/models/constants/message_types.py
wsapi_client/models/constants/presence_statuses.py
wsapi_client/models/entities/accounts/__init__.py
wsapi_client/models/entities/accounts/account_info.py
wsapi_client/models/entities/chats/chat_archive.py
wsapi_client/models/entities/chats/chat_business_profile.py
wsapi_client/models/entities/chats/chat_ephemeral.py
wsapi_client/models/entities/chats/chat_info.py
wsapi_client/models/entities/chats/chat_mute.py
wsapi_client/models/entities/chats/chat_picture.py
wsapi_client/models/entities/chats/chat_pin.py
wsapi_client/models/entities/chats/chat_read.py
wsapi_client/models/entities/contacts/contact_business_profile.py
wsapi_client/models/entities/contacts/contact_info.py
wsapi_client/models/entities/contacts/contact_picture.py
wsapi_client/models/entities/groups/group_created.py
wsapi_client/models/entities/groups/group_info.py
wsapi_client/models/entities/groups/group_invite_info.py
wsapi_client/models/entities/groups/group_invite_link.py
wsapi_client/models/entities/groups/group_join_request.py
wsapi_client/models/entities/groups/group_joined.py
wsapi_client/models/entities/groups/group_participant_info.py
wsapi_client/models/entities/groups/group_picture_info.py
wsapi_client/models/entities/groups/group_picture_updated.py
wsapi_client/models/entities/instance/__init__.py
wsapi_client/models/entities/instance/instance_settings.py
wsapi_client/models/entities/messages/__init__.py
wsapi_client-1.0.10.dist-info/METADATA
wsapi_client-1.0.10.dist-info/WHEEL
wsapi_client-1.0.10.dist-info/RECORD
