Metadata-Version: 2.4
Name: wsapi-client
Version: 1.0.10
Summary: Python SDK for WSApi: send messages, manage chats/groups, and receive events via webhooks or SSE.
Project-URL: Homepage, https://wsapi.chat
Project-URL: Repository, https://github.com/wsapi-chat/wsapi-python
Author: WSApi
License: MIT
Requires-Python: >=3.9
Requires-Dist: httpx>=0.27.0
Requires-Dist: pydantic>=2.7.0
Provides-Extra: test
Requires-Dist: flask>=3.0.0; extra == 'test'
Requires-Dist: pytest-asyncio>=0.23.0; extra == 'test'
Requires-Dist: pytest>=8.0.0; extra == 'test'
Provides-Extra: webhook
Requires-Dist: flask>=3.0.0; extra == 'webhook'
